LICENSE
MANIFEST.in
README.rst
setup.py
Mopidy_MFE.egg-info/PKG-INFO
Mopidy_MFE.egg-info/SOURCES.txt
Mopidy_MFE.egg-info/dependency_links.txt
Mopidy_MFE.egg-info/entry_points.txt
Mopidy_MFE.egg-info/not-zip-safe
Mopidy_MFE.egg-info/requires.txt
Mopidy_MFE.egg-info/top_level.txt
mopidy_mfe/__init__.py
mopidy_mfe/ext.conf
mopidy_mfe/www/app.css
mopidy_mfe/www/app.js
mopidy_mfe/www/component.css
mopidy_mfe/www/index.html
mopidy_mfe/www/manifest.json
mopidy_mfe/www/rzslider.css
mopidy_mfe/www/assets/vinyl-icon.png
mopidy_mfe/www/assets/android/Icon-144.png
mopidy_mfe/www/assets/android/Icon-192.png
mopidy_mfe/www/assets/android/Icon-36.png
mopidy_mfe/www/assets/android/Icon-48.png
mopidy_mfe/www/assets/android/Icon-72.png
mopidy_mfe/www/assets/android/Icon-96.png
mopidy_mfe/www/assets/ios/Icon-120.png
mopidy_mfe/www/assets/ios/Icon-152.png
mopidy_mfe/www/assets/ios/Icon-76.png
mopidy_mfe/www/assets/ios/Icon.png
mopidy_mfe/www/js/classie.js
mopidy_mfe/www/js/modernizr.custom.js
mopidy_mfe/www/services/cacheService.js
mopidy_mfe/www/services/lastfmService.js
mopidy_mfe/www/services/mopidyService.js
mopidy_mfe/www/services/playlistService.js
mopidy_mfe/www/services/util.js
mopidy_mfe/www/vendor/angular-route.min.js
mopidy_mfe/www/vendor/angular.min.js
mopidy_mfe/www/vendor/jquery-2.2.0.min.js
mopidy_mfe/www/vendor/lastfm.api.cache.js
mopidy_mfe/www/vendor/lastfm.api.js
mopidy_mfe/www/vendor/lastfm.api.md5.js
mopidy_mfe/www/vendor/mopidy.min.js
mopidy_mfe/www/vendor/rzslider.js
mopidy_mfe/www/vendor/underscore-min.js
mopidy_mfe/www/vendor/font-awesome/HELP-US-OUT.txt
mopidy_mfe/www/vendor/font-awesome/css/font-awesome.css
mopidy_mfe/www/vendor/font-awesome/css/font-awesome.min.css
mopidy_mfe/www/vendor/font-awesome/fonts/FontAwesome.otf
mopidy_mfe/www/vendor/font-awesome/fonts/fontawesome-webfont.eot
mopidy_mfe/www/vendor/font-awesome/fonts/fontawesome-webfont.svg
mopidy_mfe/www/vendor/font-awesome/fonts/fontawesome-webfont.ttf
mopidy_mfe/www/vendor/font-awesome/fonts/fontawesome-webfont.woff
mopidy_mfe/www/vendor/font-awesome/fonts/fontawesome-webfont.woff2
mopidy_mfe/www/vendor/font-awesome/less/animated.less
mopidy_mfe/www/vendor/font-awesome/less/bordered-pulled.less
