Metadata-Version: 1.1
Name: Mopidy-MFE
Version: 0.4.9
Summary: Web client for Mopidy
Home-page: https://github.com/LukeMcDonnell/mopidy-MFE
Author: Luke McDonnell
Author-email: lukemcdonnl@gmail.com
License: MIT License
Platform: UNKNOWN
Classifier: Development Status :: 4 - Beta
Classifier: Environment :: No Input/Output (Daemon)
Classifier: Intended Audience :: End Users/Desktop
Classifier: License :: OSI Approved :: MIT License
Classifier: Operating System :: OS Independent
Classifier: Programming Language :: Python :: 2
Classifier: Topic :: Multimedia :: Sound/Audio :: Players
